{
  "id": "82c3e85b-5fd6-477f-9b46-5c925d06dbb3",
  "prevId": "00000000-0000-0000-0000-000000000000",
  "version": "7",
  "dialect": "postgresql",
  "tables": {
    "public.banned_urls": {
      "name": "banned_urls",
      "schema": "",
      "columns": {
        "guild_id": {
          "name": "guild_id",
          "type": "varchar",
          "primaryKey": false,
          "notNull": true
        },
        "video_id": {
          "name": "video_id",
          "type": "varchar",
          "primaryKey": false,
          "notNull": true
        },
        "banned_by": {
          "name": "banned_by",
          "type": "varchar",
          "primaryKey": false,
          "notNull": true
        },
        "video_title": {
          "name": "video_title",
          "type": "varchar",
          "primaryKey": false,
          "notNull": true
        },
        "created_at": {
          "name": "created_at",
          "type": "timestamp",
          "primaryKey": false,
          "notNull": true,
          "default": "now()"
        },
        "updated_at": {
          "name": "updated_at",
          "type": "timestamp",
          "primaryKey": false,
          "notNull": true,
          "default": "now()"
        }
      },
      "indexes": {},
      "foreignKeys": {
        "banned_urls_guild_id_guilds_id_fk": {
          "name": "banned_urls_guild_id_guilds_id_fk",
          "tableFrom": "banned_urls",
          "tableTo": "guilds",
          "columnsFrom": [
            "guild_id"
          ],
          "columnsTo": [
            "id"
          ],
          "onDelete": "no action",
          "onUpdate": "no action"
        }
      },
      "compositePrimaryKeys": {
        "banned_urls_guild_id_video_id_pk": {
          "name": "banned_urls_guild_id_video_id_pk",
          "columns": [
            "guild_id",
            "video_id"
          ]
        }
      },
      "uniqueConstraints": {},
      "policies": {},
      "checkConstraints": {},
      "isRLSEnabled": false
    },
    "public.banned_words": {
      "name": "banned_words",
      "schema": "",
      "columns": {
        "guild_id": {
          "name": "guild_id",
          "type": "varchar",
          "primaryKey": false,
          "notNull": true
        },
        "keyword": {
          "name": "keyword",
          "type": "varchar",
          "primaryKey": false,
          "notNull": true
        },
        "banned_by": {
          "name": "banned_by",
          "type": "varchar",
          "primaryKey": false,
          "notNull": true
        },
        "created_at": {
          "name": "created_at",
          "type": "timestamp",
          "primaryKey": false,
          "notNull": true,
          "default": "now()"
        },
        "updated_at": {
          "name": "updated_at",
          "type": "timestamp",
          "primaryKey": false,
          "notNull": true,
          "default": "now()"
        }
      },
      "indexes": {},
      "foreignKeys": {
        "banned_words_guild_id_guilds_id_fk": {
          "name": "banned_words_guild_id_guilds_id_fk",
          "tableFrom": "banned_words",
          "tableTo": "guilds",
          "columnsFrom": [
            "guild_id"
          ],
          "columnsTo": [
            "id"
          ],
          "onDelete": "no action",
          "onUpdate": "no action"
        }
      },
      "compositePrimaryKeys": {
        "banned_words_guild_id_keyword_pk": {
          "name": "banned_words_guild_id_keyword_pk",
          "columns": [
            "guild_id",
            "keyword"
          ]
        }
      },
      "uniqueConstraints": {},
      "policies": {},
      "checkConstraints": {},
      "isRLSEnabled": false
    },
    "public.guilds": {
      "name": "guilds",
      "schema": "",
      "columns": {
        "id": {
          "name": "id",
          "type": "varchar",
          "primaryKey": true,
          "notNull": true
        },
        "prefix": {
          "name": "prefix",
          "type": "varchar",
          "primaryKey": false,
          "notNull": true
        },
        "owner_id": {
          "name": "owner_id",
          "type": "varchar",
          "primaryKey": false,
          "notNull": true
        },
        "music_channel_id": {
          "name": "music_channel_id",
          "type": "varchar",
          "primaryKey": false,
          "notNull": false
        },
        "message_id": {
          "name": "message_id",
          "type": "varchar",
          "primaryKey": false,
          "notNull": false
        },
        "created_at": {
          "name": "created_at",
          "type": "timestamp",
          "primaryKey": false,
          "notNull": true,
          "default": "now()"
        },
        "updated_at": {
          "name": "updated_at",
          "type": "timestamp",
          "primaryKey": false,
          "notNull": true,
          "default": "now()"
        }
      },
      "indexes": {},
      "foreignKeys": {},
      "compositePrimaryKeys": {},
      "uniqueConstraints": {},
      "policies": {},
      "checkConstraints": {},
      "isRLSEnabled": false
    },
    "public.play_history": {
      "name": "play_history",
      "schema": "",
      "columns": {
        "id": {
          "name": "id",
          "type": "integer",
          "primaryKey": true,
          "notNull": true,
          "identity": {
            "type": "always",
            "name": "play_history_id_seq",
            "schema": "public",
            "increment": "1",
            "startWith": "1",
            "minValue": "1",
            "maxValue": "2147483647",
            "cache": "1",
            "cycle": false
          }
        },
        "video_id": {
          "name": "video_id",
          "type": "varchar",
          "primaryKey": false,
          "notNull": true
        },
        "user_id": {
          "name": "user_id",
          "type": "varchar",
          "primaryKey": false,
          "notNull": true
        },
        "username": {
          "name": "username",
          "type": "varchar",
          "primaryKey": false,
          "notNull": true
        },
        "search_string": {
          "name": "search_string",
          "type": "varchar",
          "primaryKey": false,
          "notNull": true
        },
        "result_url": {
          "name": "result_url",
          "type": "varchar",
          "primaryKey": false,
          "notNull": true
        },
        "result_name": {
          "name": "result_name",
          "type": "varchar",
          "primaryKey": false,
          "notNull": true
        },
        "created_at": {
          "name": "created_at",
          "type": "timestamp",
          "primaryKey": false,
          "notNull": true,
          "default": "now()"
        },
        "updated_at": {
          "name": "updated_at",
          "type": "timestamp",
          "primaryKey": false,
          "notNull": true,
          "default": "now()"
        }
      },
      "indexes": {
        "play_history_video_id_idx": {
          "name": "play_history_video_id_idx",
          "columns": [
            {
              "expression": "video_id",
              "isExpression": false,
              "asc": true,
              "nulls": "last"
            }
          ],
          "isUnique": false,
          "concurrently": false,
          "method": "btree",
          "with": {}
        }
      },
      "foreignKeys": {},
      "compositePrimaryKeys": {},
      "uniqueConstraints": {},
      "policies": {},
      "checkConstraints": {},
      "isRLSEnabled": false
    }
  },
  "enums": {},
  "schemas": {},
  "sequences": {},
  "roles": {},
  "policies": {},
  "views": {},
  "_meta": {
    "columns": {},
    "schemas": {},
    "tables": {}
  }
}